transword_matcher/__init__.py
transword_matcher/main.py
transword_matcher/prompts.py
transword_matcher-2025.12.21084344.dist-info/METADATA
transword_matcher-2025.12.21084344.dist-info/WHEEL
transword_matcher-2025.12.21084344.dist-info/top_level.txt
transword_matcher-2025.12.21084344.dist-info/RECORD
