Metadata-Version: 2.4
Name: transword-matcher
Version: 2025.12.21084344
Summary: The package uses structured pattern matching to interpret user requests for language translation, extracting the source and target languages along with the text to translate. It then returns a detaile
Author-email: transword-matcher <hi@eugene.plus>
License: MIT
Project-URL: Homepage, https://github.com/chigwell/transword-matcher
Requires-Python: >=3.9
Requires-Dist: langchain-llm7>=0.0.0
Requires-Dist: llmatch-messages>=0.0.0
Requires-Dist: langchain-core>=0.3.0
